locate_pixelcolor_cython_multi_auto_compile/README.MD
locate_pixelcolor_cython_multi_auto_compile/__init__.py
locate_pixelcolor_cython_multi_auto_compile/requirements.txt
locate_pixelcolor_cython_multi_auto_compile/thirdparty.json
locate_pixelcolor_cython_multi_auto_compile-0.10.dist-info/LICENSE.rst
locate_pixelcolor_cython_multi_auto_compile-0.10.dist-info/METADATA
locate_pixelcolor_cython_multi_auto_compile-0.10.dist-info/WHEEL
locate_pixelcolor_cython_multi_auto_compile-0.10.dist-info/top_level.txt
locate_pixelcolor_cython_multi_auto_compile-0.10.dist-info/RECORD
