Metadata-Version: 2.1
Name: locate-pixelcolor-cython-multi-auto-compile
Version: 0.10
Summary: Detects colors in images 8 x faster than Numpy / Uses Cython - returns a dict
Home-page: https://github.com/hansalemaos/locate_pixelcolor_cython_multi_auto_compile
Author: Johannes Fischer
Author-email: aulasparticularesdealemaosp@gmail.com
License: MIT
Keywords: cython,compile,automatic,rgb,color,search
Classifier: Development Status :: 4 - Beta
Classifier: Programming Language :: Python :: 3 :: Only
Classifier: Programming Language :: Python :: 3.10
Classifier: Topic :: Software Development :: Libraries :: Python Modules
Classifier: Topic :: Utilities
License-File: LICENSE.rst
Requires-Dist: Cython
Requires-Dist: numpy
